compact/MCL_clustering.py
compact/__init__.py
compact/cluster_annotation.py
compact/evaluation.py
compact/main.py
compact/member_selection.py
compact/pairwise_scoring.py
compact/process_data.py
compact/reciprocal_hits.py
compact/run_compact.py
compact/utils.py
compact_bio-0.1.0.dist-info/LICENCE
compact_bio-0.1.0.dist-info/METADATA
compact_bio-0.1.0.dist-info/WHEEL
compact_bio-0.1.0.dist-info/entry_points.txt
compact_bio-0.1.0.dist-info/top_level.txt
compact_bio-0.1.0.dist-info/RECORD
